snafu-0.0.3.data/scripts/snafu
snafu-0.0.3.data/scripts/snafu-accounts
snafu-0.0.3.data/scripts/snafu-control
snafu-0.0.3.data/scripts/snafu-import
snafu-0.0.3.dist-info/DESCRIPTION.rst
snafu-0.0.3.dist-info/METADATA
snafu-0.0.3.dist-info/RECORD
snafu-0.0.3.dist-info/WHEEL
snafu-0.0.3.dist-info/metadata.json
snafu-0.0.3.dist-info/top_level.txt
snafulib/snafu.py
snafulib/snafuaccounts.py
snafulib/snafucontrol.py
snafulib/snafuimport.py
snafulib/authenticators/aws.py
snafulib/connectors/cli.py
snafulib/connectors/cron.py
snafulib/connectors/filesystem.py
snafulib/connectors/messaging.py
snafulib/connectors/web.py
snafulib/connectors/xmpp.py
snafulib/executors/c.py
snafulib/executors/docker.py
snafulib/executors/inmemory.py
snafulib/executors/inmemstateless.py
snafulib/executors/java.py
snafulib/executors/javascript.py
snafulib/executors/lxc.py
snafulib/executors/openshift.py
snafulib/executors/proxy.py
snafulib/executors/python2-exec.py
snafulib/executors/python2.py
snafulib/executors/python2stateful.py
snafulib/executors/python3-exec.py
snafulib/executors/python3-trace-exec.py
snafulib/executors/python3.py
snafulib/executors/python3trace.py
snafulib/loggers/csv.py
snafulib/loggers/sqlite.py
