Metadata-Version: 2.0
Name: snafu
Version: 0.0.3
Summary: Swiss Army Knife of Serverless Computing
Home-page: https://github.com/serviceprototypinglab/snafu
Author: Josef Spillner
Author-email: josef.spillner@zhaw.ch
License: Apache 2.0
Keywords: cloud faas serverless functions
Platform: UNKNOWN
Classifier: Development Status :: 2 - Pre-Alpha
Classifier: Environment :: Console
Classifier: Environment :: No Input/Output (Daemon)
Classifier: Intended Audience :: Science/Research
Classifier: License :: OSI Approved :: Apache Software License
Classifier: Programming Language :: Python :: 3
Classifier: Topic :: Internet :: WWW/HTTP :: WSGI :: Middleware
Requires-Dist: flask
